bridge_markup-2.7.0-py3.9-nspkg.pth
bml/about.py
bml/bml.css
bml/bml.py
bml/bml.tex
bml/bml2bss.py
bml/bml2html.py
bml/bml2latex.py
bml/bml_makedepend.py
bml/bss.py
bml/html.py
bml/latex.py
bss/__init__.py
bss/bss2bml.py
bridge_markup-2.7.0.dist-info/LICENSE.org
bridge_markup-2.7.0.dist-info/METADATA
bridge_markup-2.7.0.dist-info/WHEEL
bridge_markup-2.7.0.dist-info/entry_points.txt
bridge_markup-2.7.0.dist-info/namespace_packages.txt
bridge_markup-2.7.0.dist-info/top_level.txt
bridge_markup-2.7.0.dist-info/zip-safe
bridge_markup-2.7.0.dist-info/RECORD
