Metadata-Version: 2.1
Name: bridge-markup
Version: 2.7.0
Summary: Bridge Markup Language for creating bridge (card game) bidding documents.
Home-page: https://github.com/gpaulissen/bml
Author: Erik Sjöstrand, Gert-Jan Paulissen
Author-email: gert.jan.paulissen@gmail.com
License: MIT License
Keywords: bridge,markup
Platform: UNKNOWN
Classifier: Development Status :: 6 - Mature
Classifier: Programming Language :: Python :: 3
Classifier: Natural Language :: English
Classifier: Topic :: Utilities
Classifier: Environment :: Console
Classifier: Intended Audience :: Developers
Classifier: Operating System :: OS Independent
Classifier: License :: OSI Approved :: MIT License
License-File: LICENSE.org
Requires-Dist: bs4
Provides-Extra: test
Requires-Dist: pytest ; extra == 'test'
Requires-Dist: pytest-cov ; extra == 'test'
Requires-Dist: pytest-flakes ; extra == 'test'
Requires-Dist: pytest-pycodestyle ; extra == 'test'
Requires-Dist: flake8 ; extra == 'test'
